fifo.v
module fifo #(

    parameter DATA_WIDTH = 8,
    parameter DEPTH = 8

)(

    input clk,
    input reset,

    input wr_en,
    input rd_en,

    input [DATA_WIDTH-1:0] data_in,
    output reg [DATA_WIDTH-1:0] data_out,

    output full,
    output empty,
    output almost_full,
    output almost_empty

);

//-------------------------------------
// Memory Declaration
//-------------------------------------

reg [DATA_WIDTH-1:0] mem [0:DEPTH-1];

//-------------------------------------
// Pointer Declaration
//-------------------------------------

reg [2:0] wr_ptr;
reg [2:0] rd_ptr;

//-------------------------------------
// Counter
//-------------------------------------

reg [3:0] count;

//-------------------------------------
// Status Flags
//-------------------------------------

assign full  = (count == DEPTH);
assign empty = (count == 0);

assign almost_full = (count >= DEPTH-1);
assign almost_empty = (count <= 1);

//-------------------------------------
// FIFO Logic
//-------------------------------------

always @(posedge clk or posedge reset)
begin

    if(reset)
    begin
        wr_ptr   <= 0;
        rd_ptr   <= 0;
        count    <= 0;
        data_out <= 0;
    end

    else
    begin

        //-------------------------
        // Write Operation
        //-------------------------

        if(wr_en && !full)
        begin

            mem[wr_ptr] <= data_in;

            if(wr_ptr == DEPTH-1)
                wr_ptr <= 0;
            else
                wr_ptr <= wr_ptr + 1;

        end

        //-------------------------
        // Read Operation
        //-------------------------

        if(rd_en && !empty)
        begin

            data_out <= mem[rd_ptr];

            if(rd_ptr == DEPTH-1)
                rd_ptr <= 0;
            else
                rd_ptr <= rd_ptr + 1;

        end

        //-------------------------
        // Count Logic
        //-------------------------

        if(wr_en && !rd_en && !full)
            count <= count + 1;

        else if(rd_en && !wr_en && !empty)
            count <= count - 1;

        // If both wr_en and rd_en are HIGH,
        // count remains unchanged.

    end

end

endmodule

fifo_tb.v
`timescale 1ns/1ps

module fifo_tb;

// Parameters
parameter DATA_WIDTH = 8;
parameter DEPTH = 8;

// Inputs
reg clk;
reg reset;
reg wr_en;
reg rd_en;
reg [DATA_WIDTH-1:0] data_in;

// Outputs
wire [DATA_WIDTH-1:0] data_out;
wire full;
wire empty;
wire almost_full;
wire almost_empty;

// Instantiate FIFO

fifo #(
    .DATA_WIDTH(DATA_WIDTH),
    .DEPTH(DEPTH)
) DUT (

    .clk(clk),
    .reset(reset),

    .wr_en(wr_en),
    .rd_en(rd_en),

    .data_in(data_in),
    .data_out(data_out),

    .full(full),
    .empty(empty),
    
    .almost_full(almost_full),
    .almost_empty(almost_empty)

);

// Clock Generation
always #5 clk = ~clk;

//------------------------------------------------
// Test Sequence
//------------------------------------------------

initial
begin

    clk = 0;
    reset = 1;
    wr_en = 0;
    rd_en = 0;
    data_in = 0;

    //----------------------------
    // Reset
    //----------------------------

    #20;
    reset = 0;

    //----------------------------
    // Write 8 values
    //----------------------------

    repeat(8)
    begin
        @(posedge clk);
        wr_en = 1;
        data_in = data_in + 8'd10;
    end

    @(posedge clk);
    wr_en = 0;

    //----------------------------
    // Try writing when FULL
    //----------------------------

    @(posedge clk);
    wr_en = 1;
    data_in = 8'd200;

    @(posedge clk);
    wr_en = 0;

    //----------------------------
    // Read all values
    //----------------------------

    repeat(8)
    begin
        @(posedge clk);
        rd_en = 1;
    end

    @(posedge clk);
    rd_en = 0;

    //----------------------------
    // Try reading when EMPTY
    //----------------------------

    @(posedge clk);
    rd_en = 1;

    @(posedge clk);
    rd_en = 0;

    //----------------------------
    // Simultaneous Read & Write
    //----------------------------

    @(posedge clk);

    wr_en = 1;
    rd_en = 1;
    data_in = 8'd55;

    @(posedge clk);

    wr_en = 0;
    rd_en = 0;

    //----------------------------

    #50;

    $finish;

end

//------------------------------------------------
// Waveform
//------------------------------------------------

initial
begin

    $dumpfile("waveform/fifo.vcd");
    $dumpvars(0,fifo_tb);
    $dumpvars(0,DUT);

end

//------------------------------------------------
// Monitor
//------------------------------------------------

initial
begin

$monitor(
"Time=%0t | WR=%b RD=%b DIN=%d DOUT=%d COUNT=%d FULL=%b AFULL=%b EMPTY=%b AEMPTY=%b WR_PTR=%d RD_PTR=%d",

$time,

wr_en,
rd_en,

data_in,
data_out,

DUT.count,

full,
almost_full,
empty,
almost_empty,

DUT.wr_ptr,
DUT.rd_ptr
);

end

endmodule

waveform/fifo.vcd
$date
	Mon Jun 29 23:35:20 2026
$end
$version
	Icarus Verilog
$end
$timescale
	1ps
$end
$scope module fifo_tb $end
$var wire 1 ! full $end
$var wire 1 " empty $end
$var wire 8 # data_out [7:0] $end
$var wire 1 $ almost_full $end
$var wire 1 % almost_empty $end
$var parameter 32 & DATA_WIDTH $end
$var parameter 32 ' DEPTH $end
$var reg 1 ( clk $end
$var reg 8 ) data_in [7:0] $end
$var reg 1 * rd_en $end
$var reg 1 + reset $end
$var reg 1 , wr_en $end
$scope module DUT $end
$var wire 1 ( clk $end
$var wire 8 - data_in [7:0] $end
$var wire 1 * rd_en $end
$var wire 1 + reset $end
$var wire 1 , wr_en $end
$var wire 1 ! full $end
$var wire 1 " empty $end
$var wire 1 $ almost_full $end
$var wire 1 % almost_empty $end
$var parameter 32 . DATA_WIDTH $end
$var parameter 32 / DEPTH $end
$var reg 4 0 count [3:0] $end
$var reg 8 1 data_out [7:0] $end
$var reg 3 2 rd_ptr [2:0] $end
$var reg 3 3 wr_ptr [2:0] $end
$upscope $end
$upscope $end
$scope module fifo_tb $end
$scope module DUT $end
$upscope $end
$upscope $end
$enddefinitions $end
$comment Show the parameter values. $end
$dumpall
b1000 /
b1000 .
b1000 '
b1000 &
$end
#0
$dumpvars
b0 3
b0 2
b0 1
b0 0
b0 -
0,
1+
0*
b0 )
0(
1%
0$
b0 #
1"
0!
$end
#5000
1(
#10000
0(
#15000
1(
#20000
0(
0+
#25000
0"
b1 0
b1 3
b1010 )
b1010 -
1,
1(
#30000
0(
#35000
0%
b10 0
b10 3
b10100 )
b10100 -
1(
#40000
0(
#45000
b11 0
b11 3
b11110 )
b11110 -
1(
#50000
0(
#55000
b100 0
b100 3
b101000 )
b101000 -
1(
#60000
0(
#65000
b101 0
b101 3
b110010 )
b110010 -
1(
#70000
0(
#75000
b110 0
b110 3
b111100 )
b111100 -
1(
#80000
0(
#85000
1$
b111 0
b111 3
b1000110 )
b1000110 -
1(
#90000
0(
#95000
1!
b1000 0
b0 3
b1010000 )
b1010000 -
1(
#100000
0(
#105000
0,
1(
#110000
0(
#115000
b11001000 )
b11001000 -
1,
1(
#120000
0(
#125000
0,
1(
#130000
0(
#135000
0!
b111 0
b1 2
b1010 #
b1010 1
1*
1(
#140000
0(
#145000
0$
b110 0
b10 2
b10100 #
b10100 1
1(
#150000
0(
#155000
b101 0
b11 2
b11110 #
b11110 1
1(
#160000
0(
#165000
b100 0
b100 2
b101000 #
b101000 1
1(
#170000
0(
#175000
b11 0
b101 2
b110010 #
b110010 1
1(
#180000
0(
#185000
b10 0
b110 2
b111100 #
b111100 1
1(
#190000
0(
#195000
1%
b1 0
b111 2
b1000110 #
b1000110 1
1(
#200000
0(
#205000
1"
b0 0
b0 2
b1010000 #
b1010000 1
1(
#210000
0(
#215000
0*
1(
#220000
0(
#225000
1*
1(
#230000
0(
#235000
0*
1(
#240000
0(
#245000
b1 3
b110111 )
b110111 -
1*
1,
1(
#250000
0(
#255000
0*
0,
1(
